[
  {
    "line": 1,
    "elements": [
      {
        "line": 10,
        "name": "RealSimple Product Unavailable Smoke by validating the product unavailable text title",
        "description": "Given: Provided info about the product unavailable scenario",
        "id": "realsimple-product-unavailable-smoke;realsimple-product-unavailable-smoke-by-validating-the-product-unavailable-text-title;;2",
        "type": "scenario",
        "keyword": "Scenario Outline",
        "steps": [
          {
            "result": {
              "duration": 25879733900,
              "status": "passed"
            },
            "line": 4,
            "name": "Navigate to Product Unavailable Page where the store name is RealSimple and its respective url is https://realsimple-shop.qa2.shopnation.com/shop/misook-misook-womens-spectator-striped-a-line-dress-black-new-ivory-size-large-p0a29d83a0f56eb5fd4a59106ed14df2d.html",
            "match": {
              "arguments": [
                {
                  "val": "RealSimple",
                  "offset": 61
                },
                {
                  "val": "https://realsimple-shop.qa2.shopnation.com/shop/misook-misook-womens-spectator-striped-a-line-dress-black-new-ivory-size-large-p0a29d83a0f56eb5fd4a59106ed14df2d.html",
                  "offset": 98
                }
              ],
              "location": "RSProductUnavailableValidation.realSimpleProductUnavailableLogin(String,String)"
            },
            "keyword": "When "
          },
          {
            "result": {
              "duration": 14505672800,
              "status": "passed"
            },
            "line": 5,
            "name": "the product image is unavailable",
            "match": {
              "location": "RSProductUnavailableValidation.productUnavailableImage()"
            },
            "keyword": "When "
          },
          {
            "result": {
              "duration": 1177737200,
              "status": "passed"
            },
            "line": 6,
            "name": "close the product unavailable session",
            "match": {
              "location": "RSProductUnavailableValidation.realSimpelProductUnavailableCloseBrowser()"
            },
            "keyword": "Then "
          }
        ]
      }
    ],
    "name": "RealSimple Product Unavailable Smoke",
    "description": "",
    "id": "realsimple-product-unavailable-smoke",
    "keyword": "Feature",
    "uri": "Include/features/operations/ShopNationSmoke/realSimpleProductUnavailable.feature",
    "tags": []
  }
]